{
  "updated": "2026-01-09T21:18:39.325030",
  "sections": {
    "Major Indices": {
      "S&P 500": {
        "current": 6921.46,
        "returns": {
          "YTD": 1.1096340661748583,
          "1M": 1.1833912968477467,
          "3M": 5.630666721607436,
          "1Y": 16.951125755079623,
          "3Y": 77.83401719898563,
          "5Y": 80.96834244956442
        },
        "last_date": "2026-01-08T00:00:00"
      },
      "Dow Jones": {
        "current": 49266.11,
        "returns": {
          "YTD": 2.502575250258565,
          "1M": 3.586647600340531,
          "3M": 8.325732856049761,
          "1Y": 15.5526654032349,
          "3Y": 46.98557327258921,
          "5Y": 58.422270006691754
        },
        "last_date": "2026-01-08T00:00:00"
      },
      "NASDAQ Composite": {
        "current": 23480.02,
        "returns": {
          "YTD": 1.0241377782195027,
          "1M": -0.40917880481785573,
          "3M": 5.744754537720631,
          "1Y": 20.54091405666034,
          "3Y": 120.76713694038447,
          "5Y": 77.85226155470619
        },
        "last_date": "2026-01-08T00:00:00"
      },
      "Russell 2000 (IWM)": {
        "current": 258.27,
        "returns": {
          "YTD": 4.91956451088722,
          "1M": 2.7367834838299077,
          "3M": 8.612641406282862,
          "1Y": 16.49000947183257,
          "3Y": 45.19338880143917,
          "5Y": 26.744596902420348
        },
        "last_date": "2026-01-08T00:00:00"
      },
      "SPY ETF": {
        "current": 689.51,
        "returns": {
          "YTD": 1.113033786954487,
          "1M": 0.947235886624509,
          "3M": 5.587883985176556,
          "1Y": 17.318873006501367,
          "3Y": 83.33936035566522,
          "5Y": 92.08011811571997
        },
        "last_date": "2026-01-08T00:00:00"
      },
      "Nasdaq 100 (QQQ)": {
        "current": 620.47,
        "returns": {
          "YTD": 1.002751054028117,
          "1M": -0.7327413806895278,
          "3M": 5.2536047497879546,
          "1Y": 20.59599263755507,
          "3Y": 132.52598008536984,
          "5Y": 99.58697491290769
        },
        "last_date": "2026-01-08T00:00:00"
      }
    },
    "Sectors (SPDR ETFs)": {
      "Materials": {
        "current": 47.5,
        "returns": {
          "YTD": 4.7409040793825685,
          "1M": 10.036995596203614,
          "3M": 9.94835899180826,
          "1Y": 15.12751280945064,
          "3Y": 24.563045946718496,
          "5Y": 37.13856769592772
        },
        "last_date": "2026-01-08T00:00:00"
      },
      "Energy": {
        "current": 46.55,
        "returns": {
          "YTD": 4.115410422724208,
          "1M": 2.728313953616679,
          "3M": 10.178036345734176,
          "1Y": 9.292568340138185,
          "3Y": 18.110336113345316,
          "5Y": 171.55366028666265
        },
        "last_date": "2026-01-08T00:00:00"
      },
      "Financials": {
        "current": 55.9,
        "returns": {
          "YTD": 2.063173270038332,
          "1M": 4.917417417417402,
          "3M": 7.170245398773001,
          "1Y": 15.281501340482562,
          "3Y": 58.58156028368795,
          "5Y": 86.60266317718572
        },
        "last_date": "2026-01-08T00:00:00"
      },
      "Industrials": {
        "current": 160.17,
        "returns": {
          "YTD": 3.2555440948942582,
          "1M": 4.508678063421634,
          "3M": 6.851234156104047,
          "1Y": 20.59177834663455,
          "3Y": 59.4365916782799,
          "5Y": 83.3873942777454
        },
        "last_date": "2026-01-08T00:00:00"
      },
      "Technology": {
        "current": 144.24,
        "returns": {
          "YTD": 0.18753907063973063,
          "1M": -2.4060191074183224,
          "3M": 3.7817302711103506,
          "1Y": 24.11371928133821,
          "3Y": 133.63471736743045,
          "5Y": 129.4104736123879
        },
        "last_date": "2026-01-08T00:00:00"
      },
      "Staples": {
        "current": 78.44,
        "returns": {
          "YTD": 0.9783728115344781,
          "1M": 0.5769970509039712,
          "3M": 0.4353393085787527,
          "1Y": 1.3698630136986356,
          "3Y": 4.530916844349675,
          "5Y": 22.434326564377916
        },
        "last_date": "2026-01-08T00:00:00"
      },
      "Utilities": {
        "current": 41.99,
        "returns": {
          "YTD": -1.6397282736003604,
          "1M": -1.0414334498337285,
          "3M": -6.197782166185628,
          "1Y": 13.642514587595954,
          "3Y": 28.837273522237396,
          "5Y": 56.89688672336231
        },
        "last_date": "2026-01-08T00:00:00"
      },
      "Health Care": {
        "current": 158.12,
        "returns": {
          "YTD": 2.1447028423772663,
          "1M": 5.441451053614288,
          "3M": 11.26592076560411,
          "1Y": 12.59702342804243,
          "3Y": 18.530734632683664,
          "5Y": 38.257873843624864
        },
        "last_date": "2026-01-08T00:00:00"
      },
      "Discretionary": {
        "current": 122.92,
        "returns": {
          "YTD": 2.9394523071769596,
          "1M": 4.3933178764639536,
          "3M": 7.683816765806095,
          "1Y": 11.190512804276832,
          "3Y": 89.80500670154352,
          "5Y": 51.62411232914226
        },
        "last_date": "2026-01-08T00:00:00"
      },
      "Comm Services": {
        "current": 117.48,
        "returns": {
          "YTD": -0.20387359836900876,
          "1M": 0.9365065727296118,
          "3M": 4.148936170212769,
          "1Y": 20.789636027143743,
          "3Y": 132.7258320126783,
          "5Y": 76.57695030504166
        },
        "last_date": "2026-01-08T00:00:00"
      }
    },
    "Volatility & Credit": {
      "VIX": {
        "current": 15.45,
        "returns": {
          "YTD": 3.3444816053511683,
          "1M": -8.741878322504437,
          "3M": -28.67036011080333,
          "1Y": -12.711864406779661,
          "3Y": -29.676832043695946,
          "5Y": -28.339517625231913
        },
        "last_date": "2026-01-08T00:00:00"
      },
      "HY Spread": {
        "current": 2.76,
        "returns": {
          "YTD": -0.050000000000000266,
          "1M": -0.13000000000000034,
          "3M": -0.4200000000000004,
          "1Y": -0.08000000000000007,
          "3Y": -1.6100000000000003,
          "5Y": -1.0
        },
        "last_date": "2026-01-08T00:00:00"
      },
      "AAA Yield": {
        "current": 5.31,
        "returns": {
          "YTD": -0.15000000000000036,
          "1M": 0.04999999999999982,
          "3M": 0.09999999999999964,
          "1Y": 0.10999999999999943,
          "3Y": 0.8799999999999999,
          "5Y": 3.05
        },
        "last_date": "2025-12-01T00:00:00"
      },
      "BAA Yield": {
        "current": 5.9,
        "returns": {
          "YTD": -0.17999999999999972,
          "1M": 0.040000000000000036,
          "3M": 0.07000000000000028,
          "1Y": 0.10000000000000053,
          "3Y": 0.3100000000000005,
          "5Y": 2.74
        },
        "last_date": "2025-12-01T00:00:00"
      },
      "IG Spread": {
        "current": 4.84,
        "returns": {
          "YTD": 0.0,
          "1M": -0.040000000000000036,
          "3M": 0.05999999999999961,
          "1Y": -0.5800000000000001,
          "3Y": -0.3600000000000003,
          "5Y": 2.94
        },
        "last_date": "2026-01-08T00:00:00"
      }
    },
    "Commodities & Energy": {
      "WTI Crude": {
        "current": 58.1,
        "returns": {
          "YTD": 1.4669926650366705,
          "1M": -3.5364436327411486,
          "3M": -7.069737683941146,
          "1Y": -22.159699892818864,
          "3Y": -21.24169716687,
          "5Y": 15.163528245787905
        },
        "last_date": "2026-01-05T00:00:00"
      },
      "Brent Crude": {
        "current": 63.0,
        "returns": {
          "YTD": 2.689486552567244,
          "1M": -2.2042843837317583,
          "3M": -6.110283159463481,
          "1Y": -17.88321167883211,
          "3Y": -17.550058892815066,
          "5Y": 17.100371747211906
        },
        "last_date": "2026-01-05T00:00:00"
      },
      "Natural Gas": {
        "current": 2.82,
        "returns": {
          "YTD": -29.500000000000004,
          "1M": -45.66473988439307,
          "3M": -15.06024096385542,
          "1Y": -17.05882352941177,
          "3Y": -17.784256559766774,
          "5Y": 2.1739130434782705
        },
        "last_date": "2026-01-05T00:00:00"
      },
      "Energy Sector": {
        "current": 46.55,
        "returns": {
          "YTD": 4.115410422724208,
          "1M": 2.728313953616679,
          "3M": 10.178036345734176,
          "1Y": 9.292568340138185,
          "3Y": 18.110336113345316,
          "5Y": 171.55366028666265
        },
        "last_date": "2026-01-08T00:00:00"
      },
      "Oil & Gas E&P": {
        "current": 128.46,
        "returns": {
          "YTD": 1.7424362426738504,
          "1M": -4.526198439241924,
          "3M": 3.6302032913843263,
          "1Y": -6.689910655916309,
          "3Y": -3.3408577878103807,
          "5Y": 103.23376787748386
        },
        "last_date": "2026-01-08T00:00:00"
      }
    },
    "Interest Rates": {
      "Fed Funds Rate": {
        "current": 3.64,
        "returns": {
          "YTD": 0.0,
          "1M": -0.25,
          "3M": -0.4599999999999995,
          "1Y": -0.69,
          "3Y": -0.69,
          "5Y": 3.5500000000000003
        },
        "last_date": "2026-01-07T00:00:00"
      },
      "3-Month Treasury": {
        "current": 3.62,
        "returns": {
          "YTD": -0.04999999999999982,
          "1M": -0.10999999999999988,
          "3M": -0.39999999999999947,
          "1Y": -0.7299999999999995,
          "3Y": -1.08,
          "5Y": 3.54
        },
        "last_date": "2026-01-08T00:00:00"
      },
      "2-Year Treasury": {
        "current": 3.47,
        "returns": {
          "YTD": 0.0,
          "1M": -0.09999999999999964,
          "3M": -0.1299999999999999,
          "1Y": -0.8299999999999996,
          "3Y": -0.77,
          "5Y": 3.33
        },
        "last_date": "2026-01-07T00:00:00"
      },
      "5-Year Treasury": {
        "current": 3.7,
        "returns": {
          "YTD": -0.029999999999999805,
          "1M": -0.04999999999999982,
          "3M": -0.040000000000000036,
          "1Y": -0.7599999999999998,
          "3Y": 0.010000000000000231,
          "5Y": 3.21
        },
        "last_date": "2026-01-07T00:00:00"
      },
      "10-Year Treasury": {
        "current": 4.15,
        "returns": {
          "YTD": -0.02999999999999936,
          "1M": -0.019999999999999574,
          "3M": 0.010000000000000675,
          "1Y": -0.5199999999999996,
          "3Y": 0.6000000000000005,
          "5Y": 3.0200000000000005
        },
        "last_date": "2026-01-07T00:00:00"
      },
      "30-Year Treasury": {
        "current": 4.82,
        "returns": {
          "YTD": -0.019999999999999574,
          "1M": 0.010000000000000675,
          "3M": 0.10000000000000053,
          "1Y": -0.08999999999999986,
          "3Y": 1.1500000000000004,
          "5Y": 2.95
        },
        "last_date": "2026-01-07T00:00:00"
      }
    },
    "Real Estate & Intl": {
      "US REITs": {
        "current": 89.29,
        "returns": {
          "YTD": 0.9040569555882172,
          "1M": 0.49521665728757824,
          "3M": 1.316237376602758,
          "1Y": 1.8246094195461415,
          "3Y": 5.793838862559242,
          "5Y": 13.124407709031205
        },
        "last_date": "2026-01-08T00:00:00"
      },
      "US Real Estate": {
        "current": 94.58,
        "returns": {
          "YTD": 0.7349025455320124,
          "1M": 0.44604927782498915,
          "3M": 0.9499412957626241,
          "1Y": 3.118185782817262,
          "3Y": 9.70885048138268,
          "5Y": 18.03113386263062
        },
        "last_date": "2026-01-08T00:00:00"
      },
      "Intl Developed": {
        "current": 97.94,
        "returns": {
          "YTD": 1.9889617827762107,
          "1M": 2.6840008387502667,
          "3M": 6.179531656548143,
          "1Y": 28.496457622671212,
          "3Y": 43.14527915814088,
          "5Y": 34.26903984064291
        },
        "last_date": "2026-01-08T00:00:00"
      },
      "Emerging Markets": {
        "current": 56.87,
        "returns": {
          "YTD": 3.948089928715026,
          "1M": 4.29121584448926,
          "3M": 9.491721216788607,
          "1Y": 36.052631578947384,
          "3Y": 48.12017346234485,
          "5Y": 14.071034141077398
        },
        "last_date": "2026-01-08T00:00:00"
      },
      "30-Yr Mortgage": {
        "current": 6.16,
        "returns": {
          "YTD": 0.009999999999999787,
          "1M": -0.03000000000000025,
          "3M": -0.13999999999999968,
          "1Y": -0.75,
          "3Y": -0.3200000000000003,
          "5Y": 3.5100000000000002
        },
        "last_date": "2026-01-08T00:00:00"
      }
    }
  }
}